dataPython.py
dataPython/__init__.py
dataPython/dataPython.py
dataPython-0.3.dist-info/LICENSE
dataPython-0.3.dist-info/METADATA
dataPython-0.3.dist-info/WHEEL
dataPython-0.3.dist-info/top_level.txt
dataPython-0.3.dist-info/RECORD
